fluiddoc/__init__.py
fluiddoc/fluiddocset.py
fluiddoc/fluidnbstripout.py
fluiddoc/ipynb_maker.py
fluiddoc/mathmacro.py
fluiddyn-0.9.0.dist-info/METADATA
fluiddyn-0.9.0.dist-info/WHEEL
fluiddyn-0.9.0.dist-info/entry_points.txt
fluiddyn-0.9.0.dist-info/licenses/LICENSE.txt
fluiddyn/__init__.py
fluiddyn/calcul/__init__.py
fluiddyn/calcul/easypyfft.py
fluiddyn/calcul/setofvariables.py
fluiddyn/calcul/signal.py
fluiddyn/calcul/sphericalharmo.py
fluiddyn/calcul/test/__init__.py
fluiddyn/calcul/test/test_easypyfft.py
fluiddyn/calcul/test/test_setofvariables.py
fluiddyn/calcul/test/test_signal.py
fluiddyn/calcul/test/test_sphericalharmo.py
fluiddyn/clusters/__init__.py
fluiddyn/clusters/azzurra.py
fluiddyn/clusters/ciment.py
fluiddyn/clusters/cines.py
fluiddyn/clusters/gricad.py
fluiddyn/clusters/idris.py
fluiddyn/clusters/legi.py
fluiddyn/clusters/licallo.py
fluiddyn/clusters/local.py
fluiddyn/clusters/mesonet.py
fluiddyn/clusters/oar.py
fluiddyn/clusters/pbs.py
fluiddyn/clusters/slurm.py
fluiddyn/clusters/snic.py
fluiddyn/clusters/test/__init__.py
fluiddyn/clusters/test/test_gricad.py
fluiddyn/clusters/test/test_local.py
fluiddyn/clusters/test/test_oar.py
fluiddyn/clusters/test/test_pbs.py
fluiddyn/clusters/test/test_slurm_snic.py
fluiddyn/io/__init__.py
fluiddyn/io/binary.py
fluiddyn/io/dantec.py
fluiddyn/io/davis.py
fluiddyn/io/digiflow.py
fluiddyn/io/dump.py
fluiddyn/io/hdf5.py
fluiddyn/io/image.py
fluiddyn/io/in_py.py
fluiddyn/io/multitiff.py
fluiddyn/io/mycsv.py
fluiddyn/io/ns3d.py
fluiddyn/io/query.py
fluiddyn/io/rdvision.py
fluiddyn/io/redirect_stdout.py
fluiddyn/io/tee.py
fluiddyn/io/test/__init__.py
fluiddyn/io/test/ns3d_files/PV.t=0000.000
fluiddyn/io/test/ns3d_files/forcing_2D_info.in_L=30x30_nh=48_expLO_b=1.8_Ti=7.0_nbgene=4_d=4_T=28
fluiddyn/io/test/ns3d_files/forcing_2D_info.in_L=30x30_nh=48_expLO_b=1.8_Ti=7.0_nbgene=4_d=4_T=28_little-endian
fluiddyn/io/test/rdvision_files/Dalsa2.seq
fluiddyn/io/test/rdvision_files/Dalsa2.sqb
fluiddyn/io/test/rdvision_files/Dalsa2.xml
fluiddyn/io/test/test_binary.py
fluiddyn/io/test/test_dantec.py
fluiddyn/io/test/test_digiflow.py
fluiddyn/io/test/test_dump.py
fluiddyn-0.9.0.dist-info/RECORD
