Metadata-Version: 2.1
Name: fluiddyn
Version: 0.9.0
Summary: Framework for studying fluid dynamics.
Keywords: Fluid dynamics,research
Author-Email: Pierre Augier <pierre.augier@legi.cnrs.fr>
License: CeCILL-B License
Classifier: Development Status :: 5 - Production/Stable
Classifier: Intended Audience :: Education
Classifier: Intended Audience :: Science/Research
Classifier: License :: OSI Approved :: BSD License
Classifier: Programming Language :: Python
Classifier: Programming Language :: Python :: 3
Classifier: Programming Language :: Python :: 3.10
Classifier: Programming Language :: Python :: 3.11
Classifier: Programming Language :: Python :: 3.12
Classifier: Programming Language :: Python :: 3.13
Classifier: Programming Language :: Python :: Implementation :: CPython
Classifier: Programming Language :: Python :: Implementation :: PyPy
Classifier: Topic :: Scientific/Engineering
Project-URL: homepage, https://foss.heptapod.net/fluiddyn/fluiddyn
Project-URL: documentation, https://fluiddyn.readthedocs.io
Project-URL: twitter, https://twitter.com/pyfluiddyn
Project-URL: conda-forge, https://github.com/conda-forge/fluiddyn-feedstock
Requires-Python: >=3.10
Requires-Dist: numpy
Requires-Dist: matplotlib
Requires-Dist: h5py
Requires-Dist: h5netcdf
Requires-Dist: psutil>=5.2.1
Requires-Dist: distro
Requires-Dist: simpleeval>=0.9.13
Provides-Extra: fft
Requires-Dist: pyfftw>=0.15; extra == "fft"
Requires-Dist: pulp; extra == "fft"
Provides-Extra: mpi
Requires-Dist: mpi4py; extra == "mpi"
Provides-Extra: sht
Requires-Dist: shtns; extra == "sht"
Provides-Extra: full
Requires-Dist: fluiddyn[mpi,sht]; extra == "full"
Requires-Dist: scikit-image; extra == "full"
Requires-Dist: opencv-python; extra == "full"
